suo/__init__.py
suo/utils.py
suo/shell/__init__.py
suo/shell/usage.py
suo/src/data.yaml
suo-0.0.5.dist-info/LICENSE
suo-0.0.5.dist-info/METADATA
suo-0.0.5.dist-info/WHEEL
suo-0.0.5.dist-info/entry_points.txt
suo-0.0.5.dist-info/top_level.txt
suo-0.0.5.dist-info/zip-safe
suo-0.0.5.dist-info/RECORD
