Metadata-Version: 2.1
Name: suo
Version: 0.0.5
Summary: 中英文缩写转化
Home-page: https://github.com/Ailln/suo
Author: Ailln
Author-email: kinggreenhall@gmail.com
License: MIT License
Platform: UNKNOWN
Classifier: Programming Language :: Python :: 3
Classifier: License :: OSI Approved :: MIT License
Classifier: Operating System :: OS Independent
Requires-Python: >=3.6
Requires-Dist: setuptools (>=40.6.3)
Requires-Dist: PyYAML (>=5.1)
